LICENSE
MANIFEST.in
README.md
pyproject.toml
setup.cfg
SOURSOP.egg-info/PKG-INFO
SOURSOP.egg-info/SOURCES.txt
SOURSOP.egg-info/dependency_links.txt
SOURSOP.egg-info/not-zip-safe
SOURSOP.egg-info/requires.txt
SOURSOP.egg-info/top_level.txt
soursop/__init__.py
soursop/_internal_data.py
soursop/_version.py
soursop/configs.py
soursop/soursop.py
soursop/ssdata.py
soursop/ssexceptions.py
soursop/ssio.py
soursop/ssmutualinformation.py
soursop/ssnmr.py
soursop/sspolymer.py
soursop/sspre.py
soursop/ssprotein.py
soursop/sssampling.py
soursop/sstools.py
soursop/sstrajectory.py
soursop/ssutils.py
soursop/.ipynb_checkpoints/Untitled-checkpoint.ipynb
soursop/data/SASA_SUMMARY.csv
soursop/data/bbseg2.dat
soursop/data/phi_excluded_volume_tripeptides.pickle
soursop/data/psi_excluded_volume_tripeptides.pickle
soursop/data/test_data/all_residues.pdb
soursop/data/test_data/all_residues.xtc
soursop/data/test_data/ctl9.pdb
soursop/data/test_data/ctl9.xtc
soursop/data/test_data/gs6.dcd
soursop/data/test_data/gs6.pdb
soursop/data/test_data/gs6.xtc
soursop/data/test_data/gs6_distance_map_mean.npy
soursop/data/test_data/gs6_distance_map_std.npy
soursop/data/test_data/gs6_invalid_r1.pdb
soursop/data/test_data/ntl9.dcd
soursop/data/test_data/ntl9.pdb
soursop/data/test_data/ntl9.xtc
soursop/data/test_data/ntl9_distance_map_mean.npy
soursop/data/test_data/ntl9_distance_map_std.npy
soursop/data/test_data/.ipynb_checkpoints/Untitled-checkpoint.ipynb
soursop/data/test_data/cap_tests/ACD_start_1.pdb
soursop/data/test_data/cap_tests/ACD_start_10.pdb
soursop/data/test_data/cap_tests/ACE_NH2.pdb
soursop/data/test_data/cap_tests/ACE_NME.pdb
soursop/data/test_data/cap_tests/ACE_NME_multichain.pdb
soursop/data/test_data/cap_tests/ACE_NME_start_at_5.pdb
soursop/data/test_data/cap_tests/ACE_UCAP.pdb
soursop/data/test_data/cap_tests/FOR_NH2.pdb
soursop/data/test_data/cap_tests/FOR_NME.pdb
soursop/data/test_data/cap_tests/FOR_UCAP.pdb
soursop/data/test_data/cap_tests/UCAP_NH2.pdb
soursop/data/test_data/cap_tests/UCAP_NME.pdb
soursop/data/test_data/cap_tests/UCAP_UCAP.pdb
soursop/data/test_data/cap_tests/__START.pdb
soursop/data/test_data/gromacs1chain/top.pdb
