Metadata-Version: 2.1
Name: SOURSOP
Version: 0.2.6
Summary: Simulation analysis package for working with disordered proteins
Author-email: Alex Holehouse <alex.holehouse@wustl.edu>
License: LGPLv3
Requires-Python: >=3.7
License-File: LICENSE
Requires-Dist: numpy>=1.20.0
Requires-Dist: scipy>=1.5.0
Requires-Dist: cython
Requires-Dist: mdtraj>=1.9.5
Requires-Dist: pandas>=0.23.0
Requires-Dist: threadpoolctl>=2.2.0
Requires-Dist: natsort
Requires-Dist: matplotlib
Provides-Extra: test
Requires-Dist: pytest>=6.1.2; extra == "test"
